rag_tracer/__init__.py
rag_tracer/node_info.py
rag_tracer/rag_tracer.py
rag_tracer/trace_client.py
rag_tracer-0.1.5.dist-info/METADATA
rag_tracer-0.1.5.dist-info/WHEEL
rag_tracer-0.1.5.dist-info/top_level.txt
rag_tracer-0.1.5.dist-info/RECORD
