Metadata-Version: 2.1
Name: rag-tracer
Version: 0.1.5
Summary: A Python SDK for sending RAG trace node data
Home-page: https://livein-dev.coding.net/p/rag_workflow/d/RAG-workflow/git
Author: XiaoTeng
Author-email: sunxiaoteng925@163.com
Requires-Dist: requests
Requires-Dist: apache-skywalking
